camazing/__init__.py
camazing/core.py
camazing/feature_types.py
camazing/pixelformats.py
camazing/util.py
camazing-0.9.0.dist-info/AUTHORS.rst
camazing-0.9.0.dist-info/LICENSE
camazing-0.9.0.dist-info/METADATA
camazing-0.9.0.dist-info/WHEEL
camazing-0.9.0.dist-info/top_level.txt
camazing-0.9.0.dist-info/RECORD
