Metadata-Version: 2.1
Name: camazing
Version: 0.9.0
Summary: Machine vision library for GenICam-compliant cameras
Home-page: https://github.com/silmae/camazing
Author: Severi Jääskeläinen
Author-email: severi.jaaskelainen@gmail.com
License: MIT licence
Platform: UNKNOWN
Classifier: Development Status :: 4 - Beta
Classifier: Environment :: Console
Classifier: Intended Audience :: Developers
Classifier: Intended Audience :: Science/Research
Classifier: License :: OSI Approved :: MIT License
Classifier: Natural Language :: English
Classifier: Programming Language :: Python :: 3
Classifier: Operating System :: OS Independent
Classifier: Topic :: Software Development :: Libraries :: Python Modules
Requires-Dist: genicam2
Requires-Dist: numpy
Requires-Dist: xarray
Requires-Dist: toml
Requires-Dist: tabulate
Requires-Dist: zipfile36
Provides-Extra: docs
Requires-Dist: sphinx ; extra == 'docs'
Requires-Dist: sphinxcontrib-napoleon ; extra == 'docs'
Requires-Dist: sphinx-rtd-theme ; extra == 'docs'
Requires-Dist: sphinx-markdown-tables ; extra == 'docs'
Requires-Dist: recommonmark ; extra == 'docs'
